{
  "type": "Feature",
  "properties": {
    "gn:admin1_code":"0.0",
    "gn:asciiname":"The Settlement",
    "gn:country_code":"VG",
    "gn:dem":3,
    "gn:feature_class":"P",
    "gn:feature_code":"PPL",
    "gn:name":"The Settlement",
    "gn:population":0,
    "gn:timezone":"America/Tortola",
    "iso:country":"VG",
    "name:ell_x_preferred":[
        "\u0394\u03b5 \u03a3\u03ad\u03c4\u03bb\u03bc\u03b5\u03bd\u03c4"
    ],
    "name:eng_x_preferred":[
        "The Settlement"
    ],
    "name:kor_x_preferred":[
        "\uc138\ud2c0\uba3c\ud2b8"
    ],
    "name:pol_x_preferred":[
        "The Settlement"
    ],
    "name:swe_x_preferred":[
        "The Settlement"
    ],
    "wof:name":"The Settlement",
    "wof:placetype":"locality"
},
  "geometry": {"coordinates":[-64.31667,18.71667],"type":"Point"}
}