{
  "type": "Feature",
  "properties": {
    "gn:admin1_code":"0.0",
    "gn:asciiname":"Maya Cove",
    "gn:country_code":"VG",
    "gn:dem":-9999,
    "gn:feature_class":"P",
    "gn:feature_code":"PPL",
    "gn:name":"Maya Cove",
    "gn:population":0,
    "gn:timezone":"America/Tortola",
    "iso:country":"VG",
    "wof:name":"Maya Cove",
    "wof:placetype":"locality"
},
  "geometry": {"coordinates":[-64.56667,18.41667],"type":"Point"}
}