{
  "type": "Feature",
  "properties": {
    "gn:admin1_code":"0.0",
    "gn:asciiname":"Little Carrot Bay",
    "gn:country_code":"VG",
    "gn:dem":7,
    "gn:feature_class":"P",
    "gn:feature_code":"PPLL",
    "gn:name":"Little Carrot Bay",
    "gn:population":0,
    "gn:timezone":"America/Tortola",
    "iso:country":"VG",
    "wof:name":"Little Carrot Bay",
    "wof:placetype":"locality"
},
  "geometry": {"coordinates":[-64.67407,18.40592],"type":"Point"}
}